pyxel_utils/__init__.py
pyxel_utils/py.typed
pyxel_utils/pymunk.py
pyxel_utils-0.2.0.dist-info/METADATA
pyxel_utils-0.2.0.dist-info/WHEEL
pyxel_utils-0.2.0.dist-info/licenses/LICENSE
pyxel_utils-0.2.0.dist-info/RECORD
