Metadata-Version: 2.4
Name: pyxel-utils
Version: 0.2.0
Summary: Various utilities for game development with pyxel game engine.
Author: Reiner Gerecke
License: MIT License
License-File: LICENSE
Requires-Python: >=3.10
Provides-Extra: pymunk
Requires-Dist: pymunk; extra == 'pymunk'
